[
    {
        "name": "2-1",
        "children":
        [
            {
                "name": "Star 5",
                "chest_unopened_img": "images/StarSmall.png",
                "chest_opened_img": "images/StarSmallDim.png",
                "visibility_rules": ["Starsanity"],
                "map_locations":
                [
                    {
                        "map": "2-1",
                        "x": "1175",
                        "y": "176"
                    }
                ],
                "sections":
                [
                    {
                        "name": "Star 5",
                    }
                ]
            },
            {
                "name": "Star 1",
                "chest_unopened_img": "images/StarSmall.png",
                "chest_opened_img": "images/StarSmallDim.png",
                "visibility_rules": ["Starsanity"],
                "map_locations":
                [
                    {
                        "map": "2-1",
                        "x": "1255",
                        "y": "176"
                    }
                ],
                "sections":
                [
                    {
                        "name": "Star 1",
                    }
                ]
            },
            {
                "name": "Star 2",
                "chest_unopened_img": "images/StarSmall.png",
                "chest_opened_img": "images/StarSmallDim.png",
                "visibility_rules": ["Starsanity"],
                "map_locations":
                [
                    {
                        "map": "2-1",
                        "x": "1335",
                        "y": "176"
                    }
                ],
                "sections":
                [
                    {
                        "name": "Star 2",
                    }
                ]
            },
            {
                "name": "Star 3",
                "chest_unopened_img": "images/StarSmall.png",
                "chest_opened_img": "images/StarSmallDim.png",
                "visibility_rules": ["Starsanity"],
                "map_locations":
                [
                    {
                        "map": "2-1",
                        "x": "1415",
                        "y": "176"
                    }
                ],
                "sections":
                [
                    {
                        "name": "Star 3",
                    }
                ]
            },
            {
                "name": "Star 4",
                "chest_unopened_img": "images/StarSmall.png",
                "chest_opened_img": "images/StarSmallDim.png",
                "visibility_rules": ["Starsanity"],
                "map_locations":
                [
                    {
                        "map": "2-1",
                        "x": "1495",
                        "y": "176"
                    }
                ],
                "sections":
                [
                    {
                        "name": "Star 4",
                    }
                ]
            },
            {
                "name": "Star 6",
                "chest_unopened_img": "images/StarSmall.png",
                "chest_opened_img": "images/StarSmallDim.png",
                "visibility_rules": ["Starsanity"],
                "map_locations":
                [
                    {
                        "map": "2-1",
                        "x": "1640",
                        "y": "49"
                    }
                ],
                "sections":
                [
                    {
                        "name": "Star 6",
                    }
                ]
            },
            {
                "name": "Star 17",
                "chest_unopened_img": "images/StarSmall.png",
                "chest_opened_img": "images/StarSmallDim.png",
                "visibility_rules": ["Starsanity"],
                "map_locations":
                [
                    {
                        "map": "2-1",
                        "x": "1647",
                        "y": "622"
                    }
                ],
                "sections":
                [
                    {
                        "name": "Star 17",
                    }
                ]
            },
            {
                "name": "Star 18",
                "chest_unopened_img": "images/StarSmall.png",
                "chest_opened_img": "images/StarSmallDim.png",
                "visibility_rules": ["Starsanity"],
                "map_locations":
                [
                    {
                        "map": "2-1",
                        "x": "1423",
                        "y": "622"
                    }
                ],
                "sections":
                [
                    {
                        "name": "Star 18",
                    }
                ]
            },
            {
                "name": "Star 19",
                "chest_unopened_img": "images/StarSmall.png",
                "chest_opened_img": "images/StarSmallDim.png",
                "visibility_rules": ["Starsanity"],
                "map_locations":
                [
                    {
                        "map": "2-1",
                        "x": "2071",
                        "y": "590"
                    }
                ],
                "sections":
                [
                    {
                        "name": "Star 19",
                    }
                ]
            },
            {
                "name": "Star 11",
                "chest_unopened_img": "images/StarSmall.png",
                "chest_opened_img": "images/StarSmallDim.png",
                "visibility_rules": ["Starsanity"],
                "map_locations":
                [
                    {
                        "map": "2-1",
                        "x": "589",
                        "y": "999"
                    }
                ],
                "sections":
                [
                    {
                        "name": "Star 11",
                    }
                ]
            },
            {
                "name": "Star 12",
                "chest_unopened_img": "images/StarSmall.png",
                "chest_opened_img": "images/StarSmallDim.png",
                "visibility_rules": ["Starsanity"],
                "map_locations":
                [
                    {
                        "map": "2-1",
                        "x": "701",
                        "y": "999"
                    }
                ],
                "sections":
                [
                    {
                        "name": "Star 12",
                    }
                ]
            },
            {
                "name": "Star 13",
                "chest_unopened_img": "images/StarSmall.png",
                "chest_opened_img": "images/StarSmallDim.png",
                "visibility_rules": ["Starsanity"],
                "map_locations":
                [
                    {
                        "map": "2-1",
                        "x": "813",
                        "y": "999"
                    }
                ],
                "sections":
                [
                    {
                        "name": "Star 13",
                    }
                ]
            },
            {
                "name": "Star 14",
                "chest_unopened_img": "images/StarSmall.png",
                "chest_opened_img": "images/StarSmallDim.png",
                "visibility_rules": ["Starsanity"],
                "map_locations":
                [
                    {
                        "map": "2-1",
                        "x": "925",
                        "y": "999"
                    }
                ],
                "sections":
                [
                    {
                        "name": "Star 14",
                    }
                ]
            },
            {
                "name": "Star 15",
                "chest_unopened_img": "images/StarSmall.png",
                "chest_opened_img": "images/StarSmallDim.png",
                "visibility_rules": ["Starsanity"],
                "map_locations":
                [
                    {
                        "map": "2-1",
                        "x": "1015",
                        "y": "780"
                    }
                ],
                "sections":
                [
                    {
                        "name": "Star 15",
                    }
                ]
            },
            {
                "name": "Star 16",
                "chest_unopened_img": "images/StarSmall.png",
                "chest_opened_img": "images/StarSmallDim.png",
                "visibility_rules": ["Starsanity"],
                "map_locations":
                [
                    {
                        "map": "2-1",
                        "x": "1489",
                        "y": "889"
                    }
                ],
                "sections":
                [
                    {
                        "name": "Star 16",
                    }
                ]
            },
            {
                "name": "Star 9",
                "chest_unopened_img": "images/StarSmall.png",
                "chest_opened_img": "images/StarSmallDim.png",
                "visibility_rules": ["Starsanity"],
                "map_locations":
                [
                    {
                        "map": "2-1",
                        "x": "1512",
                        "y": "1015"
                    }
                ],
                "sections":
                [
                    {
                        "name": "Star 9",
                    }
                ]
            },
            {
                "name": "Star 7",
                "chest_unopened_img": "images/StarSmall.png",
                "chest_opened_img": "images/StarSmallDim.png",
                "visibility_rules": ["Starsanity"],
                "map_locations":
                [
                    {
                        "map": "2-1",
                        "x": "1663",
                        "y": "984"
                    }
                ],
                "sections":
                [
                    {
                        "name": "Star 7",
                    }
                ]
            },
            {
                "name": "Star 8",
                "chest_unopened_img": "images/StarSmall.png",
                "chest_opened_img": "images/StarSmallDim.png",
                "visibility_rules": ["Starsanity"],
                "map_locations":
                [
                    {
                        "map": "2-1",
                        "x": "1928",
                        "y": "984"
                    }
                ],
                "sections":
                [
                    {
                        "name": "Star 8",
                    }
                ]
            },
            {
                "name": "Star 10",
                "chest_unopened_img": "images/StarSmall.png",
                "chest_opened_img": "images/StarSmallDim.png",
                "visibility_rules": ["Starsanity"],
                "map_locations":
                [
                    {
                        "map": "2-1",
                        "x": "2071",
                        "y": "1015"
                    }
                ],
                "sections":
                [
                    {
                        "name": "Star 10",
                    }
                ]
            }
        ]
    }
]
