[
  {
    "name": "Market",
    "overlay_background": "#80000000",
    "children": [
      {
        "name": "Shooting Gallery",

        "sections": [
          {
            "name": "Reward",
            "access_rules": ["^$REACHABLE|MARKET_SHOOTING_GALLERY"],
            "chest_opened_img": "images/chest_images/bullet_bag_opened.png",
            "chest_unopened_img": "images/chest_images/bullet_bag_unopened.png",
            "visibility_rules": ["$AGE_CHECK|MARKET_SHOOTING_GALLERY"],
            "item_count": 1
          }
        ],
        "map_locations": [
          {
            "map": "Market",
            "x": 555,
            "y": 196
          }
        ]
      },
      {
        "name": "Bombchu Bowling",

        "sections": [
          {
            "name": "First Prize",
            "access_rules": ["^$REACHABLE|MARKET_BOMBCHU_BOWLING_FIRST_PRIZE"],
            "chest_opened_img": "images/chest_images/piece_of_heart_opened.png",
            "chest_unopened_img": "images/chest_images/piece_of_heart_unopened.png",
            "visibility_rules": [
              "$AGE_CHECK|MARKET_BOMBCHU_BOWLING_FIRST_PRIZE"
            ],
            "item_count": 1
          },
          {
            "name": "Second Prize",
            "access_rules": ["^$REACHABLE|MARKET_BOMBCHU_BOWLING_SECOND_PRIZE"],
            "chest_opened_img": "images/chest_images/bomb_bag_upgrade_opened.png",
            "chest_unopened_img": "images/chest_images/bomb_bag_upgrade_unopened.png",
            "visibility_rules": [
              "$AGE_CHECK|MARKET_BOMBCHU_BOWLING_SECOND_PRIZE"
            ],
            "item_count": 1
          }
        ],
        "map_locations": [
          {
            "map": "Market",
            "x": 484,
            "y": 386
          }
        ]
      },
      {
        "name": "Treasure Chest Game",

        "sections": [
          {
            "name": "Reward",
            "access_rules": ["^$REACHABLE|MARKET_TREASURE_CHEST_GAME_REWARD"],
            "chest_opened_img": "images/chest_images/piece_of_heart_opened.png",
            "chest_unopened_img": "images/chest_images/piece_of_heart_unopened.png",
            "visibility_rules": [
              "$AGE_CHECK|MARKET_TREASURE_CHEST_GAME_REWARD"
            ],
            "item_count": 1
          }
        ],
        "map_locations": [
          {
            "map": "Market",
            "x": 90,
            "y": 647
          }
        ]
      },
      {
        "name": "Guard House",

        "sections": [
          {
            "name": "10 Big Poes Reward",
            "access_rules": ["^$REACHABLE|MARKET_10_BIG_POES"],
            "visibility_rules": ["$AGE_CHECK|MARKET_10_BIG_POES"],
            "chest_opened_img": "images/chest_images/bottle_with_big_poe_opened.png",
            "chest_unopened_img": "images/chest_images/bottle_with_big_poe_unopened.png",
            "item_count": 1
          },
          {
            "name": "Child Pot",
            "access_rules": ["^$REACHABLE|MARKET_GUARD_HOUSE_CHILD_POT1"],
            "visibility_rules": [
              "$OPTION_POTS_OVERWORLD,$AGE_CHECK|MARKET_GUARD_HOUSE_CHILD_POT1"
            ],
            "chest_opened_img": "images/chest_images/pot_opened.png",
            "chest_unopened_img": "images/chest_images/pot_unopened.png",
            "item_count": 44
          },
          {
            "name": "Adult Pot",
            "access_rules": ["^$REACHABLE|MARKET_GUARD_HOUSE_ADULT_POT1"],
            "visibility_rules": [
              "$OPTION_POTS_OVERWORLD,$AGE_CHECK|MARKET_GUARD_HOUSE_ADULT_POT1"
            ],
            "chest_opened_img": "images/chest_images/pot_opened.png",
            "chest_unopened_img": "images/chest_images/pot_unopened.png",
            "item_count": 11
          },
          {
            "name": "Crate",
            "access_rules": ["^$REACHABLE|MARKET_GUARD_HOUSE_CRATE1"],
            "chest_opened_img": "images/chest_images/crate_opened.png",
            "chest_unopened_img": "images/chest_images/crate_unopened.png",
            "visibility_rules": [
              "$OPTION_CRATES_OVERWORLD,$AGE_CHECK|MARKET_GUARD_HOUSE_CRATE1"
            ],
            "item_count": 5
          },
          {
            "name": "Gold Skulltula",
            "access_rules": ["^$REACHABLE|MARKET_MARKET_GS_GUARD_HOUSE"],
            "visibility_rules": [
              "$OPTION_SKULLS_OVERWORLD,$AGE_CHECK|MARKET_MARKET_GS_GUARD_HOUSE"
            ],
            "chest_opened_img": "images/chest_images/gs_opened.png",
            "chest_unopened_img": "images/chest_images/gs_unopened.png"
          }
        ],
        "map_locations": [
          {
            "map": "Market",
            "x": 719,
            "y": 705
          }
        ]
      },
      {
        "name": "Bazaar",

        "sections": [
          {
            "name": "Item 1",
            "access_rules": ["^$REACHABLE|MARKET_BAZAAR_ITEM1"],
            "visibility_rules": [
              "$SHOP_ITEM_ACTIVE|1,$AGE_CHECK|MARKET_BAZAAR_ITEM1"
            ],
            "chest_opened_img": "images/chest_images/sold_out_opened.png",
            "chest_unopened_img": "images/chest_images/shop_item_unopened.png",
            "item_count": 1
          },
          {
            "name": "Item 2",
            "access_rules": ["^$REACHABLE|MARKET_BAZAAR_ITEM2"],
            "visibility_rules": [
              "$SHOP_ITEM_ACTIVE|2,$AGE_CHECK|MARKET_BAZAAR_ITEM2"
            ],
            "chest_opened_img": "images/chest_images/sold_out_opened.png",
            "chest_unopened_img": "images/chest_images/shop_item_unopened.png",
            "item_count": 1
          },
          {
            "name": "Item 3",
            "access_rules": ["^$REACHABLE|MARKET_BAZAAR_ITEM3"],
            "visibility_rules": [
              "$SHOP_ITEM_ACTIVE|3,$AGE_CHECK|MARKET_BAZAAR_ITEM3"
            ],
            "chest_opened_img": "images/chest_images/sold_out_opened.png",
            "chest_unopened_img": "images/chest_images/shop_item_unopened.png",
            "item_count": 1
          },
          {
            "name": "Item 4",
            "access_rules": ["^$REACHABLE|MARKET_BAZAAR_ITEM4"],
            "visibility_rules": [
              "$SHOP_ITEM_ACTIVE|4,$AGE_CHECK|MARKET_BAZAAR_ITEM4"
            ],
            "chest_opened_img": "images/chest_images/sold_out_opened.png",
            "chest_unopened_img": "images/chest_images/shop_item_unopened.png",
            "item_count": 1
          },
          {
            "name": "Item 5",
            "access_rules": ["^$REACHABLE|MARKET_BAZAAR_ITEM5"],
            "visibility_rules": [
              "$SHOP_ITEM_ACTIVE|5,$AGE_CHECK|MARKET_BAZAAR_ITEM5"
            ],
            "chest_opened_img": "images/chest_images/sold_out_opened.png",
            "chest_unopened_img": "images/chest_images/shop_item_unopened.png",
            "item_count": 1
          },
          {
            "name": "Item 6",
            "access_rules": ["^$REACHABLE|MARKET_BAZAAR_ITEM6"],
            "visibility_rules": [
              "$SHOP_ITEM_ACTIVE|6,$AGE_CHECK|MARKET_BAZAAR_ITEM6"
            ],
            "chest_opened_img": "images/chest_images/sold_out_opened.png",
            "chest_unopened_img": "images/chest_images/shop_item_unopened.png",
            "item_count": 1
          },
          {
            "name": "Item 7",
            "access_rules": ["^$REACHABLE|MARKET_BAZAAR_ITEM7"],
            "visibility_rules": [
              "$SHOP_ITEM_ACTIVE|7,$AGE_CHECK|MARKET_BAZAAR_ITEM7"
            ],
            "chest_opened_img": "images/chest_images/sold_out_opened.png",
            "chest_unopened_img": "images/chest_images/shop_item_unopened.png",
            "item_count": 1
          },
          {
            "name": "Item 8",
            "access_rules": ["^$REACHABLE|MARKET_BAZAAR_ITEM8"],
            "visibility_rules": [
              "$SHOP_ITEM_ACTIVE|8,$AGE_CHECK|MARKET_BAZAAR_ITEM8"
            ],
            "chest_opened_img": "images/chest_images/sold_out_opened.png",
            "chest_unopened_img": "images/chest_images/shop_item_unopened.png",
            "item_count": 1
          }
        ],
        "map_locations": [
          {
            "map": "Market",
            "x": 806,
            "y": 441
          }
        ]
      },
      {
        "name": "Potion Shop",

        "sections": [
          {
            "name": "Item 1",
            "access_rules": ["^$REACHABLE|MARKET_POTION_SHOP_ITEM1"],
            "visibility_rules": [
              "$SHOP_ITEM_ACTIVE|1,$AGE_CHECK|MARKET_POTION_SHOP_ITEM1"
            ],
            "chest_opened_img": "images/chest_images/sold_out_opened.png",
            "chest_unopened_img": "images/chest_images/shop_item_unopened.png",
            "item_count": 1
          },
          {
            "name": "Item 2",
            "access_rules": ["^$REACHABLE|MARKET_POTION_SHOP_ITEM2"],
            "visibility_rules": [
              "$SHOP_ITEM_ACTIVE|2,$AGE_CHECK|MARKET_POTION_SHOP_ITEM2"
            ],
            "chest_opened_img": "images/chest_images/sold_out_opened.png",
            "chest_unopened_img": "images/chest_images/shop_item_unopened.png",
            "item_count": 1
          },
          {
            "name": "Item 3",
            "access_rules": ["^$REACHABLE|MARKET_POTION_SHOP_ITEM3"],
            "visibility_rules": [
              "$SHOP_ITEM_ACTIVE|3,$AGE_CHECK|MARKET_POTION_SHOP_ITEM3"
            ],
            "chest_opened_img": "images/chest_images/sold_out_opened.png",
            "chest_unopened_img": "images/chest_images/shop_item_unopened.png",
            "item_count": 1
          },
          {
            "name": "Item 4",
            "access_rules": ["^$REACHABLE|MARKET_POTION_SHOP_ITEM4"],
            "visibility_rules": [
              "$SHOP_ITEM_ACTIVE|4,$AGE_CHECK|MARKET_POTION_SHOP_ITEM4"
            ],
            "chest_opened_img": "images/chest_images/sold_out_opened.png",
            "chest_unopened_img": "images/chest_images/shop_item_unopened.png",
            "item_count": 1
          },
          {
            "name": "Item 5",
            "access_rules": ["^$REACHABLE|MARKET_POTION_SHOP_ITEM5"],
            "visibility_rules": [
              "$SHOP_ITEM_ACTIVE|5,$AGE_CHECK|MARKET_POTION_SHOP_ITEM5"
            ],
            "chest_opened_img": "images/chest_images/sold_out_opened.png",
            "chest_unopened_img": "images/chest_images/shop_item_unopened.png",
            "item_count": 1
          },
          {
            "name": "Item 6",
            "access_rules": ["^$REACHABLE|MARKET_POTION_SHOP_ITEM6"],
            "visibility_rules": [
              "$SHOP_ITEM_ACTIVE|6,$AGE_CHECK|MARKET_POTION_SHOP_ITEM6"
            ],
            "chest_opened_img": "images/chest_images/sold_out_opened.png",
            "chest_unopened_img": "images/chest_images/shop_item_unopened.png",
            "item_count": 1
          },
          {
            "name": "Item 7",
            "access_rules": ["^$REACHABLE|MARKET_POTION_SHOP_ITEM7"],
            "visibility_rules": [
              "$SHOP_ITEM_ACTIVE|7,$AGE_CHECK|MARKET_POTION_SHOP_ITEM7"
            ],
            "chest_opened_img": "images/chest_images/sold_out_opened.png",
            "chest_unopened_img": "images/chest_images/shop_item_unopened.png",
            "item_count": 1
          },
          {
            "name": "Item 8",
            "access_rules": ["^$REACHABLE|MARKET_POTION_SHOP_ITEM8"],
            "visibility_rules": [
              "$SHOP_ITEM_ACTIVE|8,$AGE_CHECK|MARKET_POTION_SHOP_ITEM8"
            ],
            "chest_opened_img": "images/chest_images/sold_out_opened.png",
            "chest_unopened_img": "images/chest_images/shop_item_unopened.png",
            "item_count": 1
          }
        ],
        "map_locations": [
          {
            "map": "Market",
            "x": 806,
            "y": 372
          }
        ]
      },
      {
        "name": "Bombchu Shop",
        "chest_unopened_img": "/images/items/close.png",
        "chest_opened_img": "/images/items/open.png",

        "sections": [
          {
            "name": "Item 1",
            "access_rules": ["^$REACHABLE|MARKET_BOMBCHU_SHOP_ITEM1"],
            "visibility_rules": [
              "$SHOP_ITEM_ACTIVE|1,$AGE_CHECK|MARKET_BOMBCHU_SHOP_ITEM1"
            ],
            "chest_opened_img": "images/chest_images/sold_out_opened.png",
            "chest_unopened_img": "images/chest_images/shop_item_unopened.png",
            "item_count": 1
          },
          {
            "name": "Item 2",
            "access_rules": ["^$REACHABLE|MARKET_BOMBCHU_SHOP_ITEM2"],
            "visibility_rules": [
              "$SHOP_ITEM_ACTIVE|2,$AGE_CHECK|MARKET_BOMBCHU_SHOP_ITEM2"
            ],
            "chest_opened_img": "images/chest_images/sold_out_opened.png",
            "chest_unopened_img": "images/chest_images/shop_item_unopened.png",
            "item_count": 1
          },
          {
            "name": "Item 3",
            "access_rules": ["^$REACHABLE|MARKET_BOMBCHU_SHOP_ITEM3"],
            "visibility_rules": [
              "$SHOP_ITEM_ACTIVE|3,$AGE_CHECK|MARKET_BOMBCHU_SHOP_ITEM3"
            ],
            "chest_opened_img": "images/chest_images/sold_out_opened.png",
            "chest_unopened_img": "images/chest_images/shop_item_unopened.png",
            "item_count": 1
          },
          {
            "name": "Item 4",
            "access_rules": ["^$REACHABLE|MARKET_BOMBCHU_SHOP_ITEM4"],
            "visibility_rules": [
              "$SHOP_ITEM_ACTIVE|4,$AGE_CHECK|MARKET_BOMBCHU_SHOP_ITEM4"
            ],
            "chest_opened_img": "images/chest_images/sold_out_opened.png",
            "chest_unopened_img": "images/chest_images/shop_item_unopened.png",
            "item_count": 1
          },
          {
            "name": "Item 5",
            "access_rules": ["^$REACHABLE|MARKET_BOMBCHU_SHOP_ITEM5"],
            "visibility_rules": [
              "$SHOP_ITEM_ACTIVE|5,$AGE_CHECK|MARKET_BOMBCHU_SHOP_ITEM5"
            ],
            "chest_opened_img": "images/chest_images/sold_out_opened.png",
            "chest_unopened_img": "images/chest_images/shop_item_unopened.png",
            "item_count": 1
          },
          {
            "name": "Item 6",
            "access_rules": ["^$REACHABLE|MARKET_BOMBCHU_SHOP_ITEM6"],
            "visibility_rules": [
              "$SHOP_ITEM_ACTIVE|6,$AGE_CHECK|MARKET_BOMBCHU_SHOP_ITEM6"
            ],
            "chest_opened_img": "images/chest_images/sold_out_opened.png",
            "chest_unopened_img": "images/chest_images/shop_item_unopened.png",
            "item_count": 1
          },
          {
            "name": "Item 7",
            "access_rules": ["^$REACHABLE|MARKET_BOMBCHU_SHOP_ITEM7"],
            "visibility_rules": [
              "$SHOP_ITEM_ACTIVE|7,$AGE_CHECK|MARKET_BOMBCHU_SHOP_ITEM7"
            ],
            "chest_opened_img": "images/chest_images/sold_out_opened.png",
            "chest_unopened_img": "images/chest_images/shop_item_unopened.png",
            "item_count": 1
          },
          {
            "name": "Item 8",
            "access_rules": ["^$REACHABLE|MARKET_BOMBCHU_SHOP_ITEM8"],
            "visibility_rules": [
              "$SHOP_ITEM_ACTIVE|8,$AGE_CHECK|MARKET_BOMBCHU_SHOP_ITEM8"
            ],
            "chest_opened_img": "images/chest_images/sold_out_opened.png",
            "chest_unopened_img": "images/chest_images/shop_item_unopened.png",
            "item_count": 1
          }
        ],
        "map_locations": [
          {
            "map": "Market",
            "x": 360,
            "y": 558
          }
        ]
      },
      {
        "name": "Back Alley House",

        "sections": [
          {
            "name": "Pot",
            "access_rules": ["^$REACHABLE|MARKET_BACK_ALLEY_HOUSE_POT1"],
            "visibility_rules": [
              "$OPTION_POTS_OVERWORLD,$AGE_CHECK|MARKET_BACK_ALLEY_HOUSE_POT1"
            ],
            "chest_opened_img": "images/chest_images/pot_opened.png",
            "chest_unopened_img": "images/chest_images/pot_unopened.png",
            "item_count": 3
          }
        ],
        "map_locations": [
          {
            "map": "Market",
            "x": 327,
            "y": 225
          }
        ]
      },
      {
        "name": "Near Bazaar Crates",

        "sections": [
          {
            "name": "Crate",
            "access_rules": ["^$REACHABLE|MARKET_NEAR_BAZAAR_CRATE1"],
            "chest_opened_img": "images/chest_images/crate_opened.png",
            "chest_unopened_img": "images/chest_images/crate_unopened.png",
            "visibility_rules": [
              "$OPTION_CRATES_OVERWORLD,$AGE_CHECK|MARKET_NEAR_BAZAAR_CRATE1"
            ],
            "item_count": 2
          }
        ],
        "map_locations": [
          {
            "map": "Market",
            "x": 698,
            "y": 423
          }
        ]
      },
      {
        "name": "Near Shooting Gallery Crates",

        "sections": [
          {
            "name": "Crate",
            "access_rules": ["^$REACHABLE|MARKET_SHOOTING_GALLERY_CRATE1"],
            "chest_opened_img": "images/chest_images/crate_opened.png",
            "chest_unopened_img": "images/chest_images/crate_unopened.png",
            "visibility_rules": [
              "$OPTION_CRATES_OVERWORLD,$AGE_CHECK|MARKET_SHOOTING_GALLERY_CRATE1"
            ],
            "item_count": 2
          }
        ],
        "map_locations": [
          {
            "map": "Market",
            "x": 597,
            "y": 286
          }
        ]
      },
      {
        "name": "Lost Dog",

        "sections": [
          {
            "name": "Reward",
            "access_rules": ["^$REACHABLE|MARKET_LOST_DOG"],
            "chest_opened_img": "images/chest_images/piece_of_heart_opened.png",
            "chest_unopened_img": "images/chest_images/piece_of_heart_unopened.png",
            "visibility_rules": ["$AGE_CHECK|MARKET_LOST_DOG"],
            "item_count": 1
          },
          {
            "name": "House Crate",
            "access_rules": ["^$REACHABLE|MARKET_LOST_DOG_HOUSE_CRATE"],
            "chest_opened_img": "images/chest_images/crate_opened.png",
            "chest_unopened_img": "images/chest_images/crate_unopened.png",
            "visibility_rules": [
              "$OPTION_CRATES_OVERWORLD,$AGE_CHECK|MARKET_LOST_DOG_HOUSE_CRATE"
            ],
            "item_count": 1
          }
        ],
        "map_locations": [
          {
            "map": "Market",
            "x": 254,
            "y": 533
          }
        ]
      },
      {
        "name": "Temple of Time Gossip Stones",

        "sections": [
          {
            "name": "Gossip Stone Fairies",
            "access_rules": ["^$REACHABLE|MARKET_TOT_LEFT_GOSSIP_STONE_FAIRY"],
            "chest_opened_img": "images/chest_images/small_fairy_opened.png",
            "chest_unopened_img": "images/chest_images/small_fairy_unopened.png",
            "visibility_rules": [
              "$OPTION_STONE_FAIRIES,$AGE_CHECK|MARKET_TOT_LEFT_GOSSIP_STONE_FAIRY"
            ],
            "item_count": 4
          },
          {
            "name": "Gossip Stone Big Fairies",
            "access_rules": [
              "^$REACHABLE|MARKET_TOT_LEFT_GOSSIP_STONE_BIG_FAIRY"
            ],
            "chest_opened_img": "images/chest_images/big_fairy_opened.png",
            "chest_unopened_img": "images/chest_images/big_fairy_unopened.png",
            "visibility_rules": [
              "$OPTION_STONE_FAIRIES,$AGE_CHECK|MARKET_TOT_LEFT_GOSSIP_STONE_BIG_FAIRY"
            ],
            "item_count": 4
          }
        ],
        "map_locations": [
          {
            "map": "Market",
            "x": 923,
            "y": 266
          }
        ]
      },
      {
        "name": "Market Tree",

        "sections": [
          {
            "name": "Tree",
            "access_rules": ["^$REACHABLE|MARKET_TREE"],
            "visibility_rules": ["$OPTION_TREES,$AGE_CHECK|MARKET_TREE"],
            "chest_opened_img": "images/chest_images/tree_opened.png",
            "chest_unopened_img": "images/chest_images/tree_unopened.png",
            "item_count": 1
          },
          {
            "name": "Grass",
            "access_rules": ["^$REACHABLE|MARKET_MARKET_GRASS1"],
            "chest_opened_img": "images/chest_images/grass_opened.png",
            "chest_unopened_img": "images/chest_images/grass_unopened.png",
            "visibility_rules": [
              "$OPTION_GRASS_OVERWORLD,$AGE_CHECK|MARKET_MARKET_GRASS1"
            ],
            "item_count": 2
          }
        ],
        "map_locations": [
          {
            "map": "Market",
            "x": 598,
            "y": 423
          }
        ]
      },
      {
        "name": "Happy Mask Shop Grass",

        "sections": [
          {
            "name": "Grass",
            "access_rules": ["^$REACHABLE|MARKET_MARKET_GRASS3"],
            "chest_opened_img": "images/chest_images/grass_opened.png",
            "chest_unopened_img": "images/chest_images/grass_unopened.png",
            "visibility_rules": [
              "$OPTION_GRASS_OVERWORLD,$AGE_CHECK|MARKET_MARKET_GRASS3"
            ],
            "item_count": 3
          }
        ],
        "map_locations": [
          {
            "map": "Market",
            "x": 694,
            "y": 288
          }
        ]
      },
      {
        "name": "Planted Grass",

        "sections": [
          {
            "name": "Grass",
            "access_rules": ["^$REACHABLE|MARKET_MARKET_GRASS6"],
            "chest_opened_img": "images/chest_images/grass_opened.png",
            "chest_unopened_img": "images/chest_images/grass_unopened.png",
            "visibility_rules": [
              "$OPTION_GRASS_OVERWORLD,$AGE_CHECK|MARKET_MARKET_GRASS6"
            ],
            "item_count": 3
          }
        ],
        "map_locations": [
          {
            "map": "Market",
            "x": 629,
            "y": 327
          }
        ]
      }
    ]
  }
]
